mbtrack2/__init__.py
mbtrack2/impedance/__init__.py
mbtrack2/impedance/csr.py
mbtrack2/impedance/impedance_model.py
mbtrack2/impedance/resistive_wall.py
mbtrack2/impedance/resonator.py
mbtrack2/impedance/tapers.py
mbtrack2/impedance/wakefield.py
mbtrack2/instability/__init__.py
mbtrack2/instability/instabilities.py
mbtrack2/instability/ions.py
mbtrack2/tracking/__init__.py
mbtrack2/tracking/aperture.py
mbtrack2/tracking/beam_ion_effects.py
mbtrack2/tracking/element.py
mbtrack2/tracking/emfields.py
mbtrack2/tracking/excite.py
mbtrack2/tracking/feedback.py
mbtrack2/tracking/ibs.py
mbtrack2/tracking/monitors/__init__.py
mbtrack2/tracking/monitors/monitors.py
mbtrack2/tracking/monitors/plotting.py
mbtrack2/tracking/monitors/tools.py
mbtrack2/tracking/parallel.py
mbtrack2/tracking/particles.py
mbtrack2/tracking/rf.py
mbtrack2/tracking/spacecharge.py
mbtrack2/tracking/synchrotron.py
mbtrack2/tracking/wakepotential.py
mbtrack2/utilities/__init__.py
mbtrack2/utilities/beamloading.py
mbtrack2/utilities/data/Yokoya_elliptic_from_Elias_USPAS.csv
mbtrack2/utilities/misc.py
mbtrack2/utilities/optics.py
mbtrack2/utilities/read_impedance.py
mbtrack2/utilities/spectrum.py
mbtrack2-0.9.1.dist-info/LICENSE
mbtrack2-0.9.1.dist-info/METADATA
mbtrack2-0.9.1.dist-info/WHEEL
mbtrack2-0.9.1.dist-info/RECORD
