Metadata-Version: 2.3
Name: mbtrack2
Version: 0.9.1
Summary: A coherent object-oriented framework to work on collective effects in synchrotrons.
License: BSD-3-Clause
Author: Alexis Gamelin
Author-email: alexis.gamelin@synchrotron-soleil.fr
Requires-Python: >=3.10,<4.0
Classifier: License :: OSI Approved :: BSD License
Classifier: Programming Language :: Python :: 3
Classifier: Programming Language :: Python :: 3.10
Classifier: Programming Language :: Python :: 3.11
Classifier: Programming Language :: Python :: 3.12
Classifier: Programming Language :: Python :: 3.13
Requires-Dist: accelerator-toolbox (>=0.6.0)
Requires-Dist: h5py (>=3.6,<4.0)
Requires-Dist: matplotlib (>=3.5,<4.0)
Requires-Dist: mpi4py (>=4.0.1,<5.0.0)
Requires-Dist: mpmath (>=1.2.1,<2.0.0)
Requires-Dist: numpy (>=2.1,<3.0)
Requires-Dist: pandas (>=2.1,<3.0)
Requires-Dist: scipy (>=1.7,<2.0)
Requires-Dist: seaborn (>=0.12)
Project-URL: Repository, https://gitlab.synchrotron-soleil.fr/PA/collective-effects/mbtrack2
